sortpy/__init__.py
sortpy/bubble.py
sortpy/counting.py
sortpy/heap.py
sortpy/insertion.py
sortpy/merge.py
sortpy/quick.py
sortpy/shell.py
sortpy/tests/__init__.py
sortpy/tests/test_algos.py
sortpy-1.1.0.dist-info/LICENSE
sortpy-1.1.0.dist-info/WHEEL
sortpy-1.1.0.dist-info/METADATA
sortpy-1.1.0.dist-info/RECORD
