Metadata-Version: 2.1
Name: sortpy
Version: 1.1.0
Summary: Various sorting algorithms in pure python
Home-page: https://github.com/xfenix/xfsort
License: MIT
Author: Denis Anikin
Author-email: ad@xfenix.ru
Requires-Python: >=3.7,<4.0
Classifier: License :: OSI Approved :: MIT License
Classifier: Programming Language :: Python :: 3
Classifier: Programming Language :: Python :: 3.10
Classifier: Programming Language :: Python :: 3.7
Classifier: Programming Language :: Python :: 3.8
Classifier: Programming Language :: Python :: 3.9
Classifier: Topic :: Software Development :: Libraries :: Python Modules
Requires-Dist: flit
Requires-Dist: pytest
Requires-Dist: pytest-cov
Requires-Dist: pytest-xdist
